jojoapi/__init__.py
jojoapi-1.0.2.dist-info/LICENSE.txt
jojoapi-1.0.2.dist-info/METADATA
jojoapi-1.0.2.dist-info/WHEEL
jojoapi-1.0.2.dist-info/top_level.txt
jojoapi-1.0.2.dist-info/RECORD
