Metadata-Version: 2.1
Name: jojoapi
Version: 1.0.2
Summary: A package for getting data from Jojo's Bizarre Api.
Author-email: CombineSoldier14 <littlelatta@outlook.com>
Project-URL: Homepage, https://github.com/CombineSoldier14/jojoapi/tree/master
Project-URL: Issues, https://github.com/CombineSoldier14/jojoapi/issues
Classifier: Programming Language :: Python :: 3
Classifier: License :: OSI Approved :: MIT License
Classifier: Operating System :: OS Independent
Requires-Python: >=3.8
License-File: LICENSE.txt
Requires-Dist: requests
